<config xmlns="http://tail-f.com/ns/config/1.0">
  <ndus xmlns="http://com/cisco/nso/corefp/sdwan">
    <name>vEdge-ndu</name>
    <network>
      <name>LAN-1</name>
      <pre-existing-network/>
    </network>
    <network>
      <name>LAN-2</name>
      <pre-existing-network/>
    </network>
    <network>
      <name>WAN-1</name>
      <pre-existing-network/>
    </network>
    <network>
      <name>WAN-2</name>
      <pre-existing-network/>
    </network>
    <network>
      <name>int-mgmt-net</name>
    </network>
    <network>
      <name>wan-net</name>
      <pre-existing-network/>
    </network>
    <nic>
      <id>0</id>
      <network>wan-net</network>
    </nic>
    <nic>
      <id>1</id>
      <network>WAN-1</network>
    </nic>
    <nic>
      <id>2</id>
      <network>LAN-1</network>
    </nic>
    <nic>
      <id>3</id>
      <network>int-mgmt-net</network>
    </nic>
  </ndus>
</config>
